cddlparser/__init__.py
cddlparser/ast.py
cddlparser/errors.py
cddlparser/lexer.py
cddlparser/parser.py
cddlparser/py.typed
cddlparser/tokens.py
cddlparser/utils.py
cddlparser-0.5.0.dist-info/LICENSE
cddlparser-0.5.0.dist-info/METADATA
cddlparser-0.5.0.dist-info/WHEEL
cddlparser-0.5.0.dist-info/top_level.txt
cddlparser-0.5.0.dist-info/RECORD
