Metadata-Version: 2.2
Name: cddlparser
Version: 0.5.0
Summary: A CDDL parser in Python
Author-email: François Daoust <fd@tidoust.net>
License: MIT License
Project-URL: homepage, https://github.com/tidoust/cddlparser
Classifier: Development Status :: 4 - Beta
Classifier: License :: OSI Approved :: MIT License
Classifier: Operating System :: OS Independent
Classifier: Programming Language :: Python :: 3.9
Classifier: Topic :: Text Processing
Requires-Python: >=3.9
License-File: LICENSE
